marshal_client/MarshalClient.py
marshal_client/MarshalJob.py
marshal_client/MarshalJobRunner.py
marshal_client/__init__.py
marshal_client/models/Job.py
marshal_client/models/JobStatus.py
marshal_client/models/__init__.py
marshal_client-1.1.0.dist-info/LICENSE
marshal_client-1.1.0.dist-info/METADATA
marshal_client-1.1.0.dist-info/WHEEL
marshal_client-1.1.0.dist-info/top_level.txt
marshal_client-1.1.0.dist-info/RECORD
