Metadata-Version: 2.1
Name: marshal-client
Version: 1.1.0
Summary: A python client for the Marshal job running service
Home-page: https://github.com/marshaljs/python_marshal_client
Author: Michael Smith
Author-email: michael.smith.ok@gmail.com
License: UNKNOWN
Platform: UNKNOWN
Classifier: Programming Language :: Python :: 3
Classifier: Operating System :: OS Independent
Requires-Python: >=3.5
